LICENSE
README.md
setup.cfg
setup.py
chromedriver_autoinstaller/__init__.py
chromedriver_autoinstaller/utils.py
rmugicag_chromedriver_autoinstaller.egg-info/PKG-INFO
rmugicag_chromedriver_autoinstaller.egg-info/SOURCES.txt
rmugicag_chromedriver_autoinstaller.egg-info/dependency_links.txt
rmugicag_chromedriver_autoinstaller.egg-info/entry_points.txt
rmugicag_chromedriver_autoinstaller.egg-info/top_level.txt
tests/test_utils.py