Metadata-Version: 2.1
Name: rmugicag-chromedriver-autoinstaller
Version: 1.0.0
Summary: Automatically install chromedriver that supports the currently installed version of chrome.
Home-page: https://github.com/rmugicag/python-chromedriver-autoinstaller
Author: Ricardo Mugica
Author-email: rmugicag@gmail.com
License: MIT
Keywords: chromedriver chrome chromium selenium
Classifier: Development Status :: 5 - Production/Stable
Classifier: Topic :: Software Development :: Testing
Classifier: Topic :: System :: Installation/Setup
Classifier: Topic :: Software Development :: Libraries :: Python Modules
Classifier: License :: OSI Approved :: MIT License
Classifier: Programming Language :: Python :: 3
Classifier: Programming Language :: Python :: 3.6
Classifier: Programming Language :: Python :: 3.7
Classifier: Programming Language :: Python :: 3.8
Classifier: Programming Language :: Python :: 3.9
Classifier: Programming Language :: Python :: 3.10
Requires-Python: >=3.6
License-File: LICENSE
